{
  "matches": [
    {
      "matchType": "singles",
      "playerA": "Gautam sir",
      "playerB": "Satyam",
      "totalSets": 1,
      "venue": "Banglore",
      "date": "2025-03-02",
      "status": "completed",
      "id": "1740911499264",
      "points": [
        {
          "id": "1740911510267-B",
          "scorer": "B",
          "timestamp": "2025-03-02T10:31:50.267Z",
          "setNumber": 1
        },
        {
          "id": "1740911512097-B",
          "scorer": "B",
          "timestamp": "2025-03-02T10:31:52.097Z",
          "setNumber": 1
        },
        {
          "id": "1740911512371-B",
          "scorer": "B",
          "timestamp": "2025-03-02T10:31:52.371Z",
          "setNumber": 1
        },
        {
          "id": "1740911512917-B",
          "scorer": "B",
          "timestamp": "2025-03-02T10:31:52.917Z",
          "setNumber": 1
        },
        {
          "id": "1740911513067-B",
          "scorer": "B",
          "timestamp": "2025-03-02T10:31:53.067Z",
          "setNumber": 1
        },
        {
          "id": "1740911513225-B",
          "scorer": "B",
          "timestamp": "2025-03-02T10:31:53.225Z",
          "setNumber": 1
        },
        {
          "id": "1740911514163-B",
          "scorer": "B",
          "timestamp": "2025-03-02T10:31:54.163Z",
          "setNumber": 1
        },
        {
          "id": "1740911514617-B",
          "scorer": "B",
          "timestamp": "2025-03-02T10:31:54.617Z",
          "setNumber": 1
        },
        {
          "id": "1740911514814-B",
          "scorer": "B",
          "timestamp": "2025-03-02T10:31:54.814Z",
          "setNumber": 1
        },
        {
          "id": "1740911514979-B",
          "scorer": "B",
          "timestamp": "2025-03-02T10:31:54.979Z",
          "setNumber": 1
        },
        {
          "id": "1740911516017-B",
          "scorer": "B",
          "timestamp": "2025-03-02T10:31:56.017Z",
          "setNumber": 1
        },
        {
          "id": "1740911518874-B",
          "scorer": "B",
          "timestamp": "2025-03-02T10:31:58.874Z",
          "setNumber": 1
        },
        {
          "id": "1740911519847-B",
          "scorer": "B",
          "timestamp": "2025-03-02T10:31:59.847Z",
          "setNumber": 1
        },
        {
          "id": "1740911520337-B",
          "scorer": "B",
          "timestamp": "2025-03-02T10:32:00.337Z",
          "setNumber": 1
        },
        {
          "id": "1740911520661-B",
          "scorer": "B",
          "timestamp": "2025-03-02T10:32:00.661Z",
          "setNumber": 1
        },
        {
          "id": "1740911520822-B",
          "scorer": "B",
          "timestamp": "2025-03-02T10:32:00.822Z",
          "setNumber": 1
        },
        {
          "id": "1740911520974-B",
          "scorer": "B",
          "timestamp": "2025-03-02T10:32:00.974Z",
          "setNumber": 1
        },
        {
          "id": "1740911521117-B",
          "scorer": "B",
          "timestamp": "2025-03-02T10:32:01.117Z",
          "setNumber": 1
        },
        {
          "id": "1740911521269-B",
          "scorer": "B",
          "timestamp": "2025-03-02T10:32:01.269Z",
          "setNumber": 1
        },
        {
          "id": "1740911521401-B",
          "scorer": "B",
          "timestamp": "2025-03-02T10:32:01.401Z",
          "setNumber": 1
        }
      ],
      "completedSets": [
        {
          "setNumber": 1,
          "scoreA": 0,
          "scoreB": 21,
          "winner": "Satyam"
        }
      ],
      "tossWinner": "Team B",
      "servingTeam": "Team B"
    },
    {
      "matchType": "doubles",
      "teamA": {
        "player1": "Ram",
        "player2": "shyam"
      },
      "teamB": {
        "player1": "parnam",
        "player2": "tamam"
      },
      "totalSets": 1,
      "venue": "Nuhuk",
      "date": "2025-03-04",
      "status": "ongoing",
      "id": "1741083644433",
      "points": [
        {
          "id": "1741113173690-B",
          "scorer": "B",
          "timestamp": "2025-03-04T18:32:53.690Z",
          "setNumber": 1
        },
        {
          "id": "1741113174839-A",
          "scorer": "A",
          "timestamp": "2025-03-04T18:32:54.839Z",
          "setNumber": 1
        },
        {
          "id": "1741113177338-A",
          "scorer": "A",
          "timestamp": "2025-03-04T18:32:57.338Z",
          "setNumber": 1
        },
        {
          "id": "1741113178424-B",
          "scorer": "B",
          "timestamp": "2025-03-04T18:32:58.424Z",
          "setNumber": 1
        },
        {
          "id": "1741114180843-A",
          "scorer": "A",
          "timestamp": "2025-03-04T18:49:40.843Z",
          "setNumber": 1
        },
        {
          "id": "1741114181843-B",
          "scorer": "B",
          "timestamp": "2025-03-04T18:49:41.843Z",
          "setNumber": 1
        },
        {
          "id": "1741114182507-B",
          "scorer": "B",
          "timestamp": "2025-03-04T18:49:42.507Z",
          "setNumber": 1
        },
        {
          "id": "1741114183187-B",
          "scorer": "B",
          "timestamp": "2025-03-04T18:49:43.187Z",
          "setNumber": 1
        },
        {
          "id": "1741114186278-A",
          "scorer": "A",
          "timestamp": "2025-03-04T18:49:46.278Z",
          "setNumber": 1
        },
        {
          "id": "1741114187108-A",
          "scorer": "A",
          "timestamp": "2025-03-04T18:49:47.108Z",
          "setNumber": 1
        }
      ],
      "completedSets": [],
      "tossWinner": "Team A",
      "servingTeam": "Team A"
    },
    {
      "matchType": "singles",
      "totalSets": 1,
      "venue": "Dubai",
      "date": "2025-06-27",
      "status": "ongoing",
      "playerA": "Rohit",
      "playerB": "Virat",
      "id": "1741108616538",
      "points": [
        {
          "id": "1741110621181-A",
          "scorer": "A",
          "timestamp": "2025-03-04T17:50:21.181Z",
          "setNumber": 1
        },
        {
          "id": "1741111032207-A",
          "scorer": "A",
          "timestamp": "2025-03-04T17:57:12.207Z",
          "setNumber": 1
        },
        {
          "id": "1741111034223-B",
          "scorer": "B",
          "timestamp": "2025-03-04T17:57:14.223Z",
          "setNumber": 1
        },
        {
          "id": "1741111035507-A",
          "scorer": "A",
          "timestamp": "2025-03-04T17:57:15.507Z",
          "setNumber": 1
        }
      ],
      "completedSets": [],
      "tossWinner": "Team A",
      "servingTeam": "Team A"
    }
  ]
}
